fifa_queries/__init__.py
fifa_queries/main.py
fifa_queries-0.0.1.dist-info/LICENSE
fifa_queries-0.0.1.dist-info/METADATA
fifa_queries-0.0.1.dist-info/WHEEL
fifa_queries-0.0.1.dist-info/top_level.txt
fifa_queries-0.0.1.dist-info/RECORD
