Metadata-Version: 2.1
Name: fifa-queries
Version: 0.0.1
Summary: Fifa Query
Home-page: https://github.com/zelpha-5W1H/fifa_queries
Author: Tharun Kothari
Author-email: tharunkothari@yahoo.com
License: UNKNOWN
Project-URL: Bug Tracker, https://github.com/pypa/https://github.com/zelpha-5W1H/fifa_queries/
Platform: UNKNOWN
Classifier: Programming Language :: Python :: 3
Classifier: License :: OSI Approved :: MIT License
Classifier: Operating System :: OS Independent
Requires-Python: >=3.6
License-File: LICENSE
